vbi/__init__.py
vbi/_version.py
vbi/inference.py
vbi/utils.py
vbi/dataset/__init__.py
vbi/dataset/connectivity_84/centers.txt
vbi/dataset/connectivity_84/centres.txt
vbi/dataset/connectivity_84/cortical.txt
vbi/dataset/connectivity_84/tract_lengths.txt
vbi/dataset/connectivity_84/weights.txt
vbi/dataset/connectivity_88/Aud_88.txt
vbi/dataset/connectivity_88/Bold.npz
vbi/dataset/connectivity_88/Labels.txt
vbi/dataset/connectivity_88/Region_labels.txt
vbi/dataset/connectivity_88/tract_lengths.txt
vbi/dataset/connectivity_88/weights.txt
vbi/feature_extraction/__init__.py
vbi/feature_extraction/calc_features.py
vbi/feature_extraction/features.json
vbi/feature_extraction/features.py
vbi/feature_extraction/features_settings.py
vbi/feature_extraction/features_utils.py
vbi/feature_extraction/infodynamics.jar
vbi/feature_extraction/utility.py
vbi/models/__init__.py
vbi/models/cpp/__init__.py
vbi/models/cpp/damp_oscillator.py
vbi/models/cpp/jansen_rit.py
vbi/models/cpp/km.py
vbi/models/cpp/mpr.py
vbi/models/cpp/vep.py
vbi/models/cpp/wc.py
vbi/models/cpp/_src/__init__.py
vbi/models/cpp/_src/_do.cpython-310-x86_64-linux-gnu.so
vbi/models/cpp/_src/_jr_sdde.cpython-310-x86_64-linux-gnu.so
vbi/models/cpp/_src/_jr_sde.cpython-310-x86_64-linux-gnu.so
vbi/models/cpp/_src/_km_sde.cpython-310-x86_64-linux-gnu.so
vbi/models/cpp/_src/_mpr_sde.cpython-310-x86_64-linux-gnu.so
vbi/models/cpp/_src/_vep.cpython-310-x86_64-linux-gnu.so
vbi/models/cpp/_src/_wc_ode.cpython-310-x86_64-linux-gnu.so
vbi/models/cpp/_src/bold.hpp
vbi/models/cpp/_src/do.hpp
vbi/models/cpp/_src/do.i
vbi/models/cpp/_src/do.py
vbi/models/cpp/_src/do_wrap.cxx
vbi/models/cpp/_src/jr_sdde.hpp
vbi/models/cpp/_src/jr_sdde.i
vbi/models/cpp/_src/jr_sdde.py
vbi/models/cpp/_src/jr_sdde_wrap.cxx
vbi/models/cpp/_src/jr_sde.hpp
vbi/models/cpp/_src/jr_sde.i
vbi/models/cpp/_src/jr_sde.py
vbi/models/cpp/_src/jr_sde_wrap.cxx
vbi/models/cpp/_src/km_sde.hpp
vbi/models/cpp/_src/km_sde.i
vbi/models/cpp/_src/km_sde.py
vbi-0.2.dist-info/licenses/LICENSE
vbi-0.2.dist-info/METADATA
vbi-0.2.dist-info/WHEEL
vbi-0.2.dist-info/top_level.txt
vbi-0.2.dist-info/RECORD
