Metadata-Version: 2.4
Name: vbi
Version: 0.2
Summary: Virtual brain inference.
Author-email: Abolfazl Ziaeemehr <a.ziaeemehr@gmail.com>, Meysam Hashemi <meysam.hashemi@gmail.com>, Marmaduke Woodman <marmaduke.woodman@gmail.com>
License-Expression: Apache-2.0
Project-URL: homepage, https://ziaeemehr.github.io/vbi_paper/
Project-URL: repository, https://github.com/Ziaeemehr/vbi_paper
Classifier: Programming Language :: Python :: 3
Classifier: Topic :: Scientific/Engineering :: Information Analysis
Classifier: Operating System :: OS Independent
Requires-Python: >=3.8
License-File: LICENSE
Requires-Dist: wheel
Requires-Dist: numpy
Requires-Dist: scipy
Requires-Dist: numba
Requires-Dist: h5py
Requires-Dist: pandas
Requires-Dist: networkx
Requires-Dist: nbconvert
Requires-Dist: matplotlib
Requires-Dist: setuptools-scm
Requires-Dist: tqdm
Requires-Dist: sbi
Requires-Dist: torch
Requires-Dist: parameterized
Requires-Dist: scikit-learn
Requires-Dist: pycatch22
Requires-Dist: pytest
Requires-Dist: swig
Requires-Dist: rich
Provides-Extra: dev
Provides-Extra: docs
Requires-Dist: sphinx; extra == "docs"
Requires-Dist: numpydoc; extra == "docs"
Requires-Dist: nbformat; extra == "docs"
Requires-Dist: nbsphinx; extra == "docs"
Requires-Dist: cloud_sptheme; extra == "docs"
Requires-Dist: sphinx_bootstrap_theme; extra == "docs"
Provides-Extra: cu
Requires-Dist: cupy; extra == "cu"
Provides-Extra: all
Requires-Dist: pytest; extra == "all"
Requires-Dist: sphinx; extra == "all"
Requires-Dist: numpydoc; extra == "all"
Requires-Dist: nbformat; extra == "all"
Requires-Dist: nbsphinx; extra == "all"
Requires-Dist: cloud_sptheme; extra == "all"
Requires-Dist: sphinx_bootstrap_theme; extra == "all"
Requires-Dist: cupy; extra == "all"
Dynamic: license-file
